Constellation_Base-0.1.5.dist-info/DESCRIPTION.rst
Constellation_Base-0.1.5.dist-info/METADATA
Constellation_Base-0.1.5.dist-info/RECORD
Constellation_Base-0.1.5.dist-info/WHEEL
Constellation_Base-0.1.5.dist-info/metadata.json
Constellation_Base-0.1.5.dist-info/top_level.txt
constellation_base/__init__.py
constellation_base/admin.py
constellation_base/apps.py
constellation_base/forms.py
constellation_base/models.py
constellation_base/signals.py
constellation_base/tests.py
constellation_base/urls.py
constellation_base/views.py
constellation_base/migrations/0001_initial.py
constellation_base/migrations/0002_remove_sidebar.py
constellation_base/migrations/0003_localgroupaclentry.py
constellation_base/migrations/__init__.py
constellation_base/static/constellation_base/css/base.css
constellation_base/static/constellation_base/css/dashboard.css
constellation_base/static/constellation_base/css/getmdl-select.min.css
constellation_base/static/constellation_base/css/login.css
constellation_base/static/constellation_base/css/print.css
constellation_base/static/constellation_base/js/getmdl-select.min.js
constellation_base/templates/constellation_base/base.html
constellation_base/templates/constellation_base/group_list.html
constellation_base/templates/constellation_base/index.html
constellation_base/templates/constellation_base/login.html
constellation_base/templates/constellation_base/includes/footer.html
constellation_base/templates/constellation_base/includes/header.html
