Metadata-Version: 2.0
Name: Constellation-Base
Version: 0.1.5
Summary: Base components of the Constellation Suite
Home-page: https://github.com/ConstellationApps/
Author: Constellation Developers
Author-email: bugs@constellationapps.org
License: ISC License
Platform: UNKNOWN
Classifier: Environment :: Web Environment
Classifier: Framework :: Django
Classifier: Intended Audience :: Developers
Classifier: License :: OSI Approved :: ISC License (ISCL)
Classifier: Operating System :: OS Independent
Classifier: Programming Language :: Python
Classifier: Topic :: Internet :: WWW/HTTP
Classifier: Topic :: Internet :: WWW/HTTP :: Dynamic Content
Classifier: Development Status :: 4 - Beta
Requires-Dist: Pillow
Requires-Dist: django
